opd/__init__.py
opd/__main__.py
opd/clients.py
opd/clocked.py
opd/command.py
opd/decoder.py
opd/default.py
opd/encoder.py
opd/errored.py
opd/handler.py
opd/listens.py
opd/loggers.py
opd/message.py
opd/objects.py
opd/objfunc.py
opd/parsers.py
opd/persist.py
opd/repeats.py
opd/runtime.py
opd/threads.py
opd/utility.py
opd/modules/__init__.py
opd/modules/cmd.py
opd/modules/err.py
opd/modules/flt.py
opd/modules/fnd.py
opd/modules/irc.py
opd/modules/log.py
opd/modules/mod.py
opd/modules/rss.py
opd/modules/sts.py
opd/modules/tdo.py
opd/modules/thr.py
opd/modules/upt.py
opd/modules/ver.py
opd-101.dist-info/METADATA
opd-101.dist-info/WHEEL
opd-101.dist-info/top_level.txt
opd-101.dist-info/zip-safe
opd-101.dist-info/RECORD
