Metadata-Version: 2.1
Name: opd
Version: 101
Summary: operator daemon
Home-page: http://github.com/nopaths/opd
Author: No Paths <nopaths@proton.me>
Author-email: nopaths@proton.me
License: Public Domain
Platform: UNKNOWN
Classifier: Development Status :: 4 - Beta
Classifier: License :: Public Domain
Classifier: Programming Language :: Python :: 3 :: Only
Classifier: Topic :: Software Development :: Libraries :: Python Modules
